whatsapp_api/__init__.py
whatsapp_api/whatsapp_api.py
onyx_whatsapp_api-0.1.1.dist-info/METADATA
onyx_whatsapp_api-0.1.1.dist-info/WHEEL
onyx_whatsapp_api-0.1.1.dist-info/entry_points.txt
onyx_whatsapp_api-0.1.1.dist-info/top_level.txt
onyx_whatsapp_api-0.1.1.dist-info/RECORD
