Metadata-Version: 2.1
Name: onyx-whatsapp-api
Version: 0.1.1
Summary: A Python module for sending WhatsApp messages using a third-party API (https://onyxberry.com/services/wapi)
Home-page: https://onyxberry.com/services/wapi
Author: Tasaddaq Hussain
Author-email: bc110200816@gmail.com
License: MIT
Requires-Dist: requests
